omnicloudmask/__init__.py
omnicloudmask/__version__.py
omnicloudmask/cloud_mask.py
omnicloudmask/data_loaders.py
omnicloudmask/download_models.py
omnicloudmask/model_download_links.csv
omnicloudmask/model_utils.py
omnicloudmask/mps_patch.py
omnicloudmask/optimizations.py
omnicloudmask/raster_utils.py
omnicloudmask-1.7.0.dist-info/licenses/LICENSE
omnicloudmask-1.7.0.dist-info/METADATA
omnicloudmask-1.7.0.dist-info/WHEEL
omnicloudmask-1.7.0.dist-info/top_level.txt
omnicloudmask-1.7.0.dist-info/RECORD
