Metadata-Version: 2.4
Name: omnicloudmask
Version: 1.7.0
Summary: Python library for cloud and cloud shadow segmentation in high to moderate resolution satellite imagery
Author-email: Nick Wright <nicholas.wright@dpird.wa.gov.au>
License-Expression: MIT
Project-URL: Homepage, https://github.com/DPIRD-DMA/OmniCloudMask
Keywords: sentinel-2,landsat,maxar,planetscope,satellite,cloud,remote-sensing,mask,shadow
Requires-Python: >=3.9
License-File: LICENSE
Requires-Dist: gdown>=5.1.0
Requires-Dist: huggingface-hub>=0.28.1
Requires-Dist: platformdirs>=4.0.0
Requires-Dist: rasterio>=1.3
Requires-Dist: safetensors>=0.3.0
Requires-Dist: segmentation-models-pytorch>=0.5.0
Requires-Dist: timm>=0.9
Requires-Dist: torch>=2.3.0
Requires-Dist: tqdm>=4.0
Provides-Extra: legacy
Requires-Dist: fastai>=2.7; extra == "legacy"
Dynamic: license-file
